{
    "with": {
        "H": {
            "H": 42,
            "Li": 0,
            "Be": 0,
            "B": 0,
            "C": 0,
            "N": 2,
            "O": 41,
            "F": 0,
            "Na": 1,
            "Mg": 1,
            "Al": 1,
            "Si": 1,
            "P": 11,
            "S": 4,
            "Cl": 1,
            "K": 0,
            "Ca": 1,
            "Sc": 0,
            "Ti": 0,
            "V": 5,
            "Cr": 1,
            "Mn": 0,
            "Fe": 7,
            "Co": 1,
            "Ni": 1,
            "Cu": 8,
            "Zn": 0,
            "Ga": 0,
            "Ge": 0,
            "As": 12,
            "Se": 1,
            "Br": 0,
            "Rb": 0,
            "Sr": 0,
            "Y": 0,
            "Zr": 0,
            "Nb": 0,
            "Mo": 3,
            "Ru": 0,
            "Rh": 0,
            "Pd": 0,
            "Ag": 0,
            "Cd": 0,
            "In": 0,
            "Sn": 0,
            "Sb": 0,
            "Te": 2,
            "I": 0,
            "Cs": 0,
            "Ba": 0,
            "La": 0,
            "Ce": 0,
            "Pr": 0,
            "Nd": 0,
            "Sm": 0,
            "Gd": 0,
            "Dy": 0,
            "Er": 0,
            "Yb": 0,
            "Hf": 0,
            "Ta": 0,
            "W": 0,
            "Re": 0,
            "Os": 0,
            "Ir": 0,
            "Pt": 0,
            "Au": 0,
            "Hg": 0,
            "Tl": 0,
            "Pb": 4,
            "Bi": 42,
            "Th": 0,
            "U": 7
        },
        "Li": {
            "Li": 0,
            "Be": 0,
            "B": 0,
            "C": 0,
            "N": 0,
            "O": 0,
            "F": 0,
            "Na": 0,
            "Mg": 0,
            "Al": 0,
            "Si": 0,
            "P": 0,
            "S": 0,
            "Cl": 0,
            "K": 0,
            "Ca": 0,
            "Sc": 0,
            "Ti": 0,
            "V": 0,
            "Cr": 0,
            "Mn": 0,
            "Fe": 0,
            "Co": 0,
            "Ni": 0,
            "Cu": 0,
            "Zn": 0,
            "Ga": 0,
            "Ge": 0,
            "As": 0,
            "Se": 0,
            "Br": 0,
            "Rb": 0,
            "Sr": 0,
            "Y": 0,
            "Zr": 0,
            "Nb": 0,
            "Mo": 0,
            "Ru": 0,
            "Rh": 0,
            "Pd": 0,
            "Ag": 0,
            "Cd": 0,
            "In": 0,
            "Sn": 0,
            "Sb": 0,
            "Te": 0,
            "I": 0,
            "Cs": 0,
            "Ba": 0,
            "La": 0,
            "Ce": 0,
            "Pr": 0,
            "Nd": 0,
            "Sm": 0,
            "Gd": 0,
            "Dy": 0,
            "Er": 0,
            "Yb": 0,
            "Hf": 0,
            "Ta": 0,
            "W": 0,
            "Re": 0,
            "Os": 0,
            "Ir": 0,
            "Pt": 0,
            "Au": 0,
            "Hg": 0,
            "Tl": 0,
            "Pb": 0,
            "Bi": 0,
            "Th": 0,
            "U": 0
        },
        "Be": {
            "Be": 0,
            "B": 0,
            "C": 0,
            "N": 0,
            "O": 0,
            "F": 0,
            "Na": 0,
            "Mg": 0,
            "Al": 0,
            "Si": 0,
            "P": 0,
            "S": 0,
            "Cl": 0,
            "K": 0,
            "Ca": 0,
            "Sc": 0,
            "Ti": 0,
            "V": 0,
            "Cr": 0,
            "Mn": 0,
            "Fe": 0,
            "Co": 0,
            "Ni": 0,
            "Cu": 0,
            "Zn": 0,
            "Ga": 0,
            "Ge": 0,
            "As": 0,
            "Se": 0,
            "Br": 0,
            "Rb": 0,
            "Sr": 0,
            "Y": 0,
            "Zr": 0,
            "Nb": 0,
            "Mo": 0,
            "Ru": 0,
            "Rh": 0,
            "Pd": 0,
            "Ag": 0,
            "Cd": 0,
            "In": 0,
            "Sn": 0,
            "Sb": 0,
            "Te": 0,
            "I": 0,
            "Cs": 0,
            "Ba": 0,
            "La": 0,
            "Ce": 0,
            "Pr": 0,
            "Nd": 0,
            "Sm": 0,
            "Gd": 0,
            "Dy": 0,
            "Er": 0,
            "Yb": 0,
            "Hf": 0,
            "Ta": 0,
            "W": 0,
            "Re": 0,
            "Os": 0,
            "Ir": 0,
            "Pt": 0,
            "Au": 0,
            "Hg": 0,
            "Tl": 0,
            "Pb": 0,
            "Bi": 0,
            "Th": 0,
            "U": 0
        },
        "B": {
            "B": 0,
            "C": 0,
            "N": 0,
            "O": 0,
            "F": 0,
            "Na": 0,
            "Mg": 0,
            "Al": 0,
            "Si": 0,
            "P": 0,
            "S": 0,
            "Cl": 0,
            "K": 0,
            "Ca": 0,
            "Sc": 0,
            "Ti": 0,
            "V": 0,
            "Cr": 0,
            "Mn": 0,
            "Fe": 0,
            "Co": 0,
            "Ni": 0,
            "Cu": 0,
            "Zn": 0,
            "Ga": 0,
            "Ge": 0,
            "As": 0,
            "Se": 0,
            "Br": 0,
            "Rb": 0,
            "Sr": 0,
            "Y": 0,
            "Zr": 0,
            "Nb": 0,
            "Mo": 0,
            "Ru": 0,
            "Rh": 0,
            "Pd": 0,
            "Ag": 0,
            "Cd": 0,
            "In": 0,
            "Sn": 0,
            "Sb": 0,
            "Te": 0,
            "I": 0,
            "Cs": 0,
            "Ba": 0,
            "La": 0,
            "Ce": 0,
            "Pr": 0,
            "Nd": 0,
            "Sm": 0,
            "Gd": 0,
            "Dy": 0,
            "Er": 0,
            "Yb": 0,
            "Hf": 0,
            "Ta": 0,
            "W": 0,
            "Re": 0,
            "Os": 0,
            "Ir": 0,
            "Pt": 0,
            "Au": 0,
            "Hg": 0,
            "Tl": 0,
            "Pb": 0,
            "Bi": 0,
            "Th": 0,
            "U": 0
        },
        "C": {
            "C": 3,
            "N": 0,
            "O": 3,
            "F": 1,
            "Na": 0,
            "Mg": 0,
            "Al": 0,
            "Si": 0,
            "P": 0,
            "S": 0,
            "Cl": 0,
            "K": 0,
            "Ca": 2,
            "Sc": 0,
            "Ti": 0,
            "V": 0,
            "Cr": 0,
            "Mn": 0,
            "Fe": 0,
            "Co": 0,
            "Ni": 0,
            "Cu": 0,
            "Zn": 0,
            "Ga": 0,
            "Ge": 0,
            "As": 0,
            "Se": 0,
            "Br": 0,
            "Rb": 0,
            "Sr": 0,
            "Y": 0,
            "Zr": 0,
            "Nb": 0,
            "Mo": 0,
            "Ru": 0,
            "Rh": 0,
            "Pd": 0,
            "Ag": 0,
            "Cd": 0,
            "In": 0,
            "Sn": 0,
            "Sb": 0,
            "Te": 0,
            "I": 0,
            "Cs": 0,
            "Ba": 0,
            "La": 0,
            "Ce": 0,
            "Pr": 0,
            "Nd": 0,
            "Sm": 0,
            "Gd": 0,
            "Dy": 0,
            "Er": 0,
            "Yb": 0,
            "Hf": 0,
            "Ta": 0,
            "W": 0,
            "Re": 0,
            "Os": 0,
            "Ir": 0,
            "Pt": 0,
            "Au": 0,
            "Hg": 0,
            "Tl": 0,
            "Pb": 0,
            "Bi": 3,
            "Th": 0,
            "U": 0
        },
        "N": {
            "N": 2,
            "O": 1,
            "F": 0,
            "Na": 1,
            "Mg": 0,
            "Al": 0,
            "Si": 0,
            "P": 0,
            "S": 1,
            "Cl": 1,
            "K": 0,
            "Ca": 0,
            "Sc": 0,
            "Ti": 0,
            "V": 0,
            "Cr": 0,
            "Mn": 0,
            "Fe": 0,
            "Co": 0,
            "Ni": 0,
            "Cu": 0,
            "Zn": 0,
            "Ga": 0,
            "Ge": 0,
            "As": 0,
            "Se": 0,
            "Br": 0,
            "Rb": 0,
            "Sr": 0,
            "Y": 0,
            "Zr": 0,
            "Nb": 0,
            "Mo": 0,
            "Ru": 0,
            "Rh": 0,
            "Pd": 0,
            "Ag": 0,
            "Cd": 0,
            "In": 0,
            "Sn": 0,
            "Sb": 0,
            "Te": 0,
            "I": 0,
            "Cs": 0,
            "Ba": 0,
            "La": 0,
            "Ce": 0,
            "Pr": 0,
            "Nd": 0,
            "Sm": 0,
            "Gd": 0,
            "Dy": 0,
            "Er": 0,
            "Yb": 0,
            "Hf": 0,
            "Ta": 0,
            "W": 0,
            "Re": 0,
            "Os": 0,
            "Ir": 0,
            "Pt": 0,
            "Au": 0,
            "Hg": 0,
            "Tl": 0,
            "Pb": 0,
            "Bi": 2,
            "Th": 0,
            "U": 0
        },
        "O": {
            "O": 83,
            "F": 3,
            "Na": 5,
            "Mg": 1,
            "Al": 1,
            "Si": 3,
            "P": 12,
            "S": 11,
            "Cl": 5,
            "K": 1,
            "Ca": 3,
            "Sc": 0,
            "Ti": 0,
            "V": 8,
            "Cr": 2,
            "Mn": 0,
            "Fe": 10,
            "Co": 2,
            "Ni": 2,
            "Cu": 12,
            "Zn": 0,
            "Ga": 0,
            "Ge": 0,
            "As": 18,
            "Se": 2,
            "Br": 0,
            "Rb": 0,
            "Sr": 0,
            "Y": 0,
            "Zr": 0,
            "Nb": 1,
            "Mo": 7,
            "Ru": 0,
            "Rh": 0,
            "Pd": 0,
            "Ag": 0,
            "Cd": 0,
            "In": 0,
            "Sn": 0,
            "Sb": 1,
            "Te": 7,
            "I": 0,
            "Cs": 0,
            "Ba": 0,
            "La": 0,
            "Ce": 0,
            "Pr": 0,
            "Nd": 0,
            "Sm": 0,
            "Gd": 0,
            "Dy": 0,
            "Er": 0,
            "Yb": 0,
            "Hf": 0,
            "Ta": 3,
            "W": 1,
            "Re": 0,
            "Os": 0,
            "Ir": 0,
            "Pt": 0,
            "Au": 0,
            "Hg": 0,
            "Tl": 1,
            "Pb": 5,
            "Bi": 83,
            "Th": 0,
            "U": 7
        },
        "F": {
            "F": 4,
            "Na": 1,
            "Mg": 0,
            "Al": 0,
            "Si": 0,
            "P": 0,
            "S": 0,
            "Cl": 0,
            "K": 0,
            "Ca": 1,
            "Sc": 0,
            "Ti": 0,
            "V": 0,
            "Cr": 0,
            "Mn": 0,
            "Fe": 0,
            "Co": 0,
            "Ni": 0,
            "Cu": 0,
            "Zn": 0,
            "Ga": 0,
            "Ge": 0,
            "As": 0,
            "Se": 0,
            "Br": 0,
            "Rb": 0,
            "Sr": 0,
            "Y": 0,
            "Zr": 0,
            "Nb": 0,
            "Mo": 0,
            "Ru": 0,
            "Rh": 0,
            "Pd": 0,
            "Ag": 0,
            "Cd": 0,
            "In": 0,
            "Sn": 0,
            "Sb": 0,
            "Te": 0,
            "I": 0,
            "Cs": 0,
            "Ba": 0,
            "La": 0,
            "Ce": 0,
            "Pr": 0,
            "Nd": 0,
            "Sm": 0,
            "Gd": 0,
            "Dy": 0,
            "Er": 0,
            "Yb": 0,
            "Hf": 0,
            "Ta": 1,
            "W": 0,
            "Re": 0,
            "Os": 0,
            "Ir": 0,
            "Pt": 0,
            "Au": 0,
            "Hg": 0,
            "Tl": 0,
            "Pb": 0,
            "Bi": 4,
            "Th": 0,
            "U": 0
        },
        "Na": {
            "Na": 5,
            "Mg": 0,
            "Al": 0,
            "Si": 0,
            "P": 0,
            "S": 3,
            "Cl": 1,
            "K": 0,
            "Ca": 0,
            "Sc": 0,
            "Ti": 0,
            "V": 0,
            "Cr": 0,
            "Mn": 0,
            "Fe": 0,
            "Co": 0,
            "Ni": 0,
            "Cu": 1,
            "Zn": 0,
            "Ga": 0,
            "Ge": 0,
            "As": 0,
            "Se": 0,
            "Br": 0,
            "Rb": 0,
            "Sr": 0,
            "Y": 0,
            "Zr": 0,
            "Nb": 0,
            "Mo": 1,
            "Ru": 0,
            "Rh": 0,
            "Pd": 0,
            "Ag": 0,
            "Cd": 0,
            "In": 0,
            "Sn": 0,
            "Sb": 0,
            "Te": 0,
            "I": 0,
            "Cs": 0,
            "Ba": 0,
            "La": 0,
            "Ce": 0,
            "Pr": 0,
            "Nd": 0,
            "Sm": 0,
            "Gd": 0,
            "Dy": 0,
            "Er": 0,
            "Yb": 0,
            "Hf": 0,
            "Ta": 1,
            "W": 0,
            "Re": 0,
            "Os": 0,
            "Ir": 0,
            "Pt": 0,
            "Au": 0,
            "Hg": 0,
            "Tl": 0,
            "Pb": 0,
            "Bi": 5,
            "Th": 0,
            "U": 0
        },
        "Mg": {
            "Mg": 1,
            "Al": 0,
            "Si": 0,
            "P": 0,
            "S": 0,
            "Cl": 0,
            "K": 0,
            "Ca": 0,
            "Sc": 0,
            "Ti": 0,
            "V": 0,
            "Cr": 0,
            "Mn": 0,
            "Fe": 1,
            "Co": 0,
            "Ni": 0,
            "Cu": 0,
            "Zn": 0,
            "Ga": 0,
            "Ge": 0,
            "As": 1,
            "Se": 0,
            "Br": 0,
            "Rb": 0,
            "Sr": 0,
            "Y": 0,
            "Zr": 0,
            "Nb": 0,
            "Mo": 0,
            "Ru": 0,
            "Rh": 0,
            "Pd": 0,
            "Ag": 0,
            "Cd": 0,
            "In": 0,
            "Sn": 0,
            "Sb": 0,
            "Te": 0,
            "I": 0,
            "Cs": 0,
            "Ba": 0,
            "La": 0,
            "Ce": 0,
            "Pr": 0,
            "Nd": 0,
            "Sm": 0,
            "Gd": 0,
            "Dy": 0,
            "Er": 0,
            "Yb": 0,
            "Hf": 0,
            "Ta": 0,
            "W": 0,
            "Re": 0,
            "Os": 0,
            "Ir": 0,
            "Pt": 0,
            "Au": 0,
            "Hg": 0,
            "Tl": 0,
            "Pb": 0,
            "Bi": 1,
            "Th": 0,
            "U": 0
        },
        "Al": {
            "Al": 1,
            "Si": 0,
            "P": 1,
            "S": 0,
            "Cl": 0,
            "K": 0,
            "Ca": 0,
            "Sc": 0,
            "Ti": 0,
            "V": 0,
            "Cr": 0,
            "Mn": 0,
            "Fe": 0,
            "Co": 0,
            "Ni": 0,
            "Cu": 0,
            "Zn": 0,
            "Ga": 0,
            "Ge": 0,
            "As": 0,
            "Se": 0,
            "Br": 0,
            "Rb": 0,
            "Sr": 0,
            "Y": 0,
            "Zr": 0,
            "Nb": 0,
            "Mo": 0,
            "Ru": 0,
            "Rh": 0,
            "Pd": 0,
            "Ag": 0,
            "Cd": 0,
            "In": 0,
            "Sn": 0,
            "Sb": 0,
            "Te": 0,
            "I": 0,
            "Cs": 0,
            "Ba": 0,
            "La": 0,
            "Ce": 0,
            "Pr": 0,
            "Nd": 0,
            "Sm": 0,
            "Gd": 0,
            "Dy": 0,
            "Er": 0,
            "Yb": 0,
            "Hf": 0,
            "Ta": 0,
            "W": 0,
            "Re": 0,
            "Os": 0,
            "Ir": 0,
            "Pt": 0,
            "Au": 0,
            "Hg": 0,
            "Tl": 0,
            "Pb": 0,
            "Bi": 1,
            "Th": 0,
            "U": 0
        },
        "Si": {
            "Si": 3,
            "P": 0,
            "S": 0,
            "Cl": 0,
            "K": 0,
            "Ca": 0,
            "Sc": 0,
            "Ti": 0,
            "V": 0,
            "Cr": 0,
            "Mn": 0,
            "Fe": 1,
            "Co": 0,
            "Ni": 0,
            "Cu": 0,
            "Zn": 0,
            "Ga": 0,
            "Ge": 0,
            "As": 0,
            "Se": 0,
            "Br": 0,
            "Rb": 0,
            "Sr": 0,
            "Y": 0,
            "Zr": 0,
            "Nb": 0,
            "Mo": 0,
            "Ru": 0,
            "Rh": 0,
            "Pd": 0,
            "Ag": 0,
            "Cd": 0,
            "In": 0,
            "Sn": 0,
            "Sb": 0,
            "Te": 0,
            "I": 0,
            "Cs": 0,
            "Ba": 0,
            "La": 0,
            "Ce": 0,
            "Pr": 0,
            "Nd": 0,
            "Sm": 0,
            "Gd": 0,
            "Dy": 0,
            "Er": 0,
            "Yb": 0,
            "Hf": 0,
            "Ta": 0,
            "W": 0,
            "Re": 0,
            "Os": 0,
            "Ir": 0,
            "Pt": 0,
            "Au": 0,
            "Hg": 0,
            "Tl": 0,
            "Pb": 0,
            "Bi": 3,
            "Th": 0,
            "U": 0
        },
        "P": {
            "P": 12,
            "S": 0,
            "Cl": 0,
            "K": 0,
            "Ca": 1,
            "Sc": 0,
            "Ti": 0,
            "V": 0,
            "Cr": 0,
            "Mn": 0,
            "Fe": 3,
            "Co": 0,
            "Ni": 0,
            "Cu": 2,
            "Zn": 0,
            "Ga": 0,
            "Ge": 0,
            "As": 1,
            "Se": 0,
            "Br": 0,
            "Rb": 0,
            "Sr": 0,
            "Y": 0,
            "Zr": 0,
            "Nb": 0,
            "Mo": 0,
            "Ru": 0,
            "Rh": 0,
            "Pd": 0,
            "Ag": 0,
            "Cd": 0,
            "In": 0,
            "Sn": 0,
            "Sb": 0,
            "Te": 0,
            "I": 0,
            "Cs": 0,
            "Ba": 0,
            "La": 0,
            "Ce": 0,
            "Pr": 0,
            "Nd": 0,
            "Sm": 0,
            "Gd": 0,
            "Dy": 0,
            "Er": 0,
            "Yb": 0,
            "Hf": 0,
            "Ta": 0,
            "W": 0,
            "Re": 0,
            "Os": 0,
            "Ir": 0,
            "Pt": 0,
            "Au": 0,
            "Hg": 0,
            "Tl": 0,
            "Pb": 1,
            "Bi": 12,
            "Th": 0,
            "U": 3
        },
        "S": {
            "S": 117,
            "Cl": 4,
            "K": 1,
            "Ca": 0,
            "Sc": 0,
            "Ti": 0,
            "V": 0,
            "Cr": 0,
            "Mn": 1,
            "Fe": 4,
            "Co": 0,
            "Ni": 6,
            "Cu": 44,
            "Zn": 0,
            "Ga": 0,
            "Ge": 0,
            "As": 3,
            "Se": 3,
            "Br": 1,
            "Rb": 0,
            "Sr": 0,
            "Y": 0,
            "Zr": 0,
            "Nb": 0,
            "Mo": 0,
            "Ru": 0,
            "Rh": 0,
            "Pd": 3,
            "Ag": 28,
            "Cd": 1,
            "In": 2,
            "Sn": 3,
            "Sb": 9,
            "Te": 12,
            "I": 1,
            "Cs": 0,
            "Ba": 0,
            "La": 0,
            "Ce": 0,
            "Pr": 0,
            "Nd": 0,
            "Sm": 0,
            "Gd": 0,
            "Dy": 0,
            "Er": 0,
            "Yb": 0,
            "Hf": 0,
            "Ta": 0,
            "W": 0,
            "Re": 0,
            "Os": 0,
            "Ir": 1,
            "Pt": 2,
            "Au": 3,
            "Hg": 1,
            "Tl": 1,
            "Pb": 63,
            "Bi": 117,
            "Th": 0,
            "U": 0
        },
        "Cl": {
            "Cl": 9,
            "K": 1,
            "Ca": 0,
            "Sc": 0,
            "Ti": 0,
            "V": 0,
            "Cr": 0,
            "Mn": 0,
            "Fe": 1,
            "Co": 0,
            "Ni": 0,
            "Cu": 2,
            "Zn": 0,
            "Ga": 0,
            "Ge": 0,
            "As": 0,
            "Se": 1,
            "Br": 0,
            "Rb": 0,
            "Sr": 0,
            "Y": 0,
            "Zr": 0,
            "Nb": 0,
            "Mo": 0,
            "Ru": 0,
            "Rh": 0,
            "Pd": 0,
            "Ag": 0,
            "Cd": 0,
            "In": 0,
            "Sn": 1,
            "Sb": 0,
            "Te": 0,
            "I": 0,
            "Cs": 0,
            "Ba": 0,
            "La": 0,
            "Ce": 0,
            "Pr": 0,
            "Nd": 0,
            "Sm": 0,
            "Gd": 0,
            "Dy": 0,
            "Er": 0,
            "Yb": 0,
            "Hf": 0,
            "Ta": 0,
            "W": 0,
            "Re": 0,
            "Os": 0,
            "Ir": 0,
            "Pt": 0,
            "Au": 0,
            "Hg": 0,
            "Tl": 1,
            "Pb": 2,
            "Bi": 9,
            "Th": 0,
            "U": 0
        },
        "K": {
            "K": 1,
            "Ca": 0,
            "Sc": 0,
            "Ti": 0,
            "V": 0,
            "Cr": 0,
            "Mn": 0,
            "Fe": 1,
            "Co": 0,
            "Ni": 0,
            "Cu": 1,
            "Zn": 0,
            "Ga": 0,
            "Ge": 0,
            "As": 0,
            "Se": 0,
            "Br": 0,
            "Rb": 0,
            "Sr": 0,
            "Y": 0,
            "Zr": 0,
            "Nb": 0,
            "Mo": 0,
            "Ru": 0,
            "Rh": 0,
            "Pd": 0,
            "Ag": 0,
            "Cd": 0,
            "In": 0,
            "Sn": 0,
            "Sb": 0,
            "Te": 0,
            "I": 0,
            "Cs": 0,
            "Ba": 0,
            "La": 0,
            "Ce": 0,
            "Pr": 0,
            "Nd": 0,
            "Sm": 0,
            "Gd": 0,
            "Dy": 0,
            "Er": 0,
            "Yb": 0,
            "Hf": 0,
            "Ta": 0,
            "W": 0,
            "Re": 0,
            "Os": 0,
            "Ir": 0,
            "Pt": 0,
            "Au": 0,
            "Hg": 0,
            "Tl": 0,
            "Pb": 0,
            "Bi": 1,
            "Th": 0,
            "U": 0
        },
        "Ca": {
            "Ca": 3,
            "Sc": 0,
            "Ti": 0,
            "V": 0,
            "Cr": 0,
            "Mn": 0,
            "Fe": 0,
            "Co": 0,
            "Ni": 0,
            "Cu": 1,
            "Zn": 0,
            "Ga": 0,
            "Ge": 0,
            "As": 0,
            "Se": 0,
            "Br": 0,
            "Rb": 0,
            "Sr": 0,
            "Y": 0,
            "Zr": 0,
            "Nb": 0,
            "Mo": 0,
            "Ru": 0,
            "Rh": 0,
            "Pd": 0,
            "Ag": 0,
            "Cd": 0,
            "In": 0,
            "Sn": 0,
            "Sb": 0,
            "Te": 0,
            "I": 0,
            "Cs": 0,
            "Ba": 0,
            "La": 0,
            "Ce": 0,
            "Pr": 0,
            "Nd": 0,
            "Sm": 0,
            "Gd": 0,
            "Dy": 0,
            "Er": 0,
            "Yb": 0,
            "Hf": 0,
            "Ta": 0,
            "W": 0,
            "Re": 0,
            "Os": 0,
            "Ir": 0,
            "Pt": 0,
            "Au": 0,
            "Hg": 0,
            "Tl": 0,
            "Pb": 0,
            "Bi": 3,
            "Th": 0,
            "U": 0
        },
        "Sc": {
            "Sc": 0,
            "Ti": 0,
            "V": 0,
            "Cr": 0,
            "Mn": 0,
            "Fe": 0,
            "Co": 0,
            "Ni": 0,
            "Cu": 0,
            "Zn": 0,
            "Ga": 0,
            "Ge": 0,
            "As": 0,
            "Se": 0,
            "Br": 0,
            "Rb": 0,
            "Sr": 0,
            "Y": 0,
            "Zr": 0,
            "Nb": 0,
            "Mo": 0,
            "Ru": 0,
            "Rh": 0,
            "Pd": 0,
            "Ag": 0,
            "Cd": 0,
            "In": 0,
            "Sn": 0,
            "Sb": 0,
            "Te": 0,
            "I": 0,
            "Cs": 0,
            "Ba": 0,
            "La": 0,
            "Ce": 0,
            "Pr": 0,
            "Nd": 0,
            "Sm": 0,
            "Gd": 0,
            "Dy": 0,
            "Er": 0,
            "Yb": 0,
            "Hf": 0,
            "Ta": 0,
            "W": 0,
            "Re": 0,
            "Os": 0,
            "Ir": 0,
            "Pt": 0,
            "Au": 0,
            "Hg": 0,
            "Tl": 0,
            "Pb": 0,
            "Bi": 0,
            "Th": 0,
            "U": 0
        },
        "Ti": {
            "Ti": 0,
            "V": 0,
            "Cr": 0,
            "Mn": 0,
            "Fe": 0,
            "Co": 0,
            "Ni": 0,
            "Cu": 0,
            "Zn": 0,
            "Ga": 0,
            "Ge": 0,
            "As": 0,
            "Se": 0,
            "Br": 0,
            "Rb": 0,
            "Sr": 0,
            "Y": 0,
            "Zr": 0,
            "Nb": 0,
            "Mo": 0,
            "Ru": 0,
            "Rh": 0,
            "Pd": 0,
            "Ag": 0,
            "Cd": 0,
            "In": 0,
            "Sn": 0,
            "Sb": 0,
            "Te": 0,
            "I": 0,
            "Cs": 0,
            "Ba": 0,
            "La": 0,
            "Ce": 0,
            "Pr": 0,
            "Nd": 0,
            "Sm": 0,
            "Gd": 0,
            "Dy": 0,
            "Er": 0,
            "Yb": 0,
            "Hf": 0,
            "Ta": 0,
            "W": 0,
            "Re": 0,
            "Os": 0,
            "Ir": 0,
            "Pt": 0,
            "Au": 0,
            "Hg": 0,
            "Tl": 0,
            "Pb": 0,
            "Bi": 0,
            "Th": 0,
            "U": 0
        },
        "V": {
            "V": 8,
            "Cr": 0,
            "Mn": 0,
            "Fe": 0,
            "Co": 0,
            "Ni": 0,
            "Cu": 2,
            "Zn": 0,
            "Ga": 0,
            "Ge": 0,
            "As": 0,
            "Se": 0,
            "Br": 0,
            "Rb": 0,
            "Sr": 0,
            "Y": 0,
            "Zr": 0,
            "Nb": 0,
            "Mo": 0,
            "Ru": 0,
            "Rh": 0,
            "Pd": 0,
            "Ag": 0,
            "Cd": 0,
            "In": 0,
            "Sn": 0,
            "Sb": 0,
            "Te": 0,
            "I": 0,
            "Cs": 0,
            "Ba": 0,
            "La": 0,
            "Ce": 0,
            "Pr": 0,
            "Nd": 0,
            "Sm": 0,
            "Gd": 0,
            "Dy": 0,
            "Er": 0,
            "Yb": 0,
            "Hf": 0,
            "Ta": 0,
            "W": 0,
            "Re": 0,
            "Os": 0,
            "Ir": 0,
            "Pt": 0,
            "Au": 0,
            "Hg": 0,
            "Tl": 0,
            "Pb": 1,
            "Bi": 8,
            "Th": 0,
            "U": 0
        },
        "Cr": {
            "Cr": 2,
            "Mn": 0,
            "Fe": 0,
            "Co": 0,
            "Ni": 0,
            "Cu": 0,
            "Zn": 0,
            "Ga": 0,
            "Ge": 0,
            "As": 0,
            "Se": 0,
            "Br": 0,
            "Rb": 0,
            "Sr": 0,
            "Y": 0,
            "Zr": 0,
            "Nb": 0,
            "Mo": 0,
            "Ru": 0,
            "Rh": 0,
            "Pd": 0,
            "Ag": 0,
            "Cd": 0,
            "In": 0,
            "Sn": 0,
            "Sb": 0,
            "Te": 0,
            "I": 0,
            "Cs": 0,
            "Ba": 0,
            "La": 0,
            "Ce": 0,
            "Pr": 0,
            "Nd": 0,
            "Sm": 0,
            "Gd": 0,
            "Dy": 0,
            "Er": 0,
            "Yb": 0,
            "Hf": 0,
            "Ta": 0,
            "W": 0,
            "Re": 0,
            "Os": 0,
            "Ir": 0,
            "Pt": 0,
            "Au": 0,
            "Hg": 0,
            "Tl": 0,
            "Pb": 0,
            "Bi": 2,
            "Th": 0,
            "U": 0
        },
        "Mn": {
            "Mn": 1,
            "Fe": 0,
            "Co": 0,
            "Ni": 0,
            "Cu": 0,
            "Zn": 0,
            "Ga": 0,
            "Ge": 0,
            "As": 0,
            "Se": 0,
            "Br": 0,
            "Rb": 0,
            "Sr": 0,
            "Y": 0,
            "Zr": 0,
            "Nb": 0,
            "Mo": 0,
            "Ru": 0,
            "Rh": 0,
            "Pd": 0,
            "Ag": 0,
            "Cd": 0,
            "In": 0,
            "Sn": 0,
            "Sb": 0,
            "Te": 0,
            "I": 0,
            "Cs": 0,
            "Ba": 0,
            "La": 0,
            "Ce": 0,
            "Pr": 0,
            "Nd": 0,
            "Sm": 0,
            "Gd": 0,
            "Dy": 0,
            "Er": 0,
            "Yb": 0,
            "Hf": 0,
            "Ta": 0,
            "W": 0,
            "Re": 0,
            "Os": 0,
            "Ir": 0,
            "Pt": 0,
            "Au": 0,
            "Hg": 0,
            "Tl": 0,
            "Pb": 0,
            "Bi": 1,
            "Th": 0,
            "U": 0
        },
        "Fe": {
            "Fe": 13,
            "Co": 1,
            "Ni": 0,
            "Cu": 4,
            "Zn": 0,
            "Ga": 0,
            "Ge": 0,
            "As": 4,
            "Se": 0,
            "Br": 0,
            "Rb": 0,
            "Sr": 0,
            "Y": 0,
            "Zr": 0,
            "Nb": 0,
            "Mo": 0,
            "Ru": 0,
            "Rh": 0,
            "Pd": 0,
            "Ag": 0,
            "Cd": 0,
            "In": 0,
            "Sn": 0,
            "Sb": 1,
            "Te": 1,
            "I": 0,
            "Cs": 0,
            "Ba": 0,
            "La": 0,
            "Ce": 0,
            "Pr": 0,
            "Nd": 0,
            "Sm": 0,
            "Gd": 0,
            "Dy": 0,
            "Er": 0,
            "Yb": 0,
            "Hf": 0,
            "Ta": 0,
            "W": 0,
            "Re": 0,
            "Os": 0,
            "Ir": 0,
            "Pt": 0,
            "Au": 0,
            "Hg": 0,
            "Tl": 0,
            "Pb": 1,
            "Bi": 13,
            "Th": 0,
            "U": 0
        },
        "Co": {
            "Co": 2,
            "Ni": 0,
            "Cu": 0,
            "Zn": 0,
            "Ga": 0,
            "Ge": 0,
            "As": 2,
            "Se": 0,
            "Br": 0,
            "Rb": 0,
            "Sr": 0,
            "Y": 0,
            "Zr": 0,
            "Nb": 0,
            "Mo": 0,
            "Ru": 0,
            "Rh": 0,
            "Pd": 0,
            "Ag": 0,
            "Cd": 0,
            "In": 0,
            "Sn": 0,
            "Sb": 0,
            "Te": 0,
            "I": 0,
            "Cs": 0,
            "Ba": 0,
            "La": 0,
            "Ce": 0,
            "Pr": 0,
            "Nd": 0,
            "Sm": 0,
            "Gd": 0,
            "Dy": 0,
            "Er": 0,
            "Yb": 0,
            "Hf": 0,
            "Ta": 0,
            "W": 0,
            "Re": 0,
            "Os": 0,
            "Ir": 0,
            "Pt": 0,
            "Au": 0,
            "Hg": 0,
            "Tl": 0,
            "Pb": 0,
            "Bi": 2,
            "Th": 0,
            "U": 0
        },
        "Ni": {
            "Ni": 9,
            "Cu": 1,
            "Zn": 0,
            "Ga": 0,
            "Ge": 0,
            "As": 3,
            "Se": 0,
            "Br": 0,
            "Rb": 0,
            "Sr": 0,
            "Y": 0,
            "Zr": 0,
            "Nb": 0,
            "Mo": 0,
            "Ru": 0,
            "Rh": 0,
            "Pd": 0,
            "Ag": 0,
            "Cd": 0,
            "In": 0,
            "Sn": 0,
            "Sb": 1,
            "Te": 2,
            "I": 0,
            "Cs": 0,
            "Ba": 0,
            "La": 0,
            "Ce": 0,
            "Pr": 0,
            "Nd": 0,
            "Sm": 0,
            "Gd": 0,
            "Dy": 0,
            "Er": 0,
            "Yb": 0,
            "Hf": 0,
            "Ta": 0,
            "W": 0,
            "Re": 0,
            "Os": 0,
            "Ir": 0,
            "Pt": 0,
            "Au": 0,
            "Hg": 0,
            "Tl": 0,
            "Pb": 0,
            "Bi": 9,
            "Th": 0,
            "U": 0
        },
        "Cu": {
            "Cu": 63,
            "Zn": 0,
            "Ga": 0,
            "Ge": 0,
            "As": 3,
            "Se": 12,
            "Br": 0,
            "Rb": 0,
            "Sr": 0,
            "Y": 0,
            "Zr": 0,
            "Nb": 0,
            "Mo": 0,
            "Ru": 0,
            "Rh": 0,
            "Pd": 2,
            "Ag": 11,
            "Cd": 0,
            "In": 0,
            "Sn": 1,
            "Sb": 1,
            "Te": 0,
            "I": 0,
            "Cs": 0,
            "Ba": 0,
            "La": 0,
            "Ce": 0,
            "Pr": 0,
            "Nd": 0,
            "Sm": 0,
            "Gd": 0,
            "Dy": 0,
            "Er": 0,
            "Yb": 0,
            "Hf": 0,
            "Ta": 0,
            "W": 0,
            "Re": 0,
            "Os": 0,
            "Ir": 0,
            "Pt": 1,
            "Au": 0,
            "Hg": 2,
            "Tl": 0,
            "Pb": 39,
            "Bi": 63,
            "Th": 0,
            "U": 0
        },
        "Zn": {
            "Zn": 0,
            "Ga": 0,
            "Ge": 0,
            "As": 0,
            "Se": 0,
            "Br": 0,
            "Rb": 0,
            "Sr": 0,
            "Y": 0,
            "Zr": 0,
            "Nb": 0,
            "Mo": 0,
            "Ru": 0,
            "Rh": 0,
            "Pd": 0,
            "Ag": 0,
            "Cd": 0,
            "In": 0,
            "Sn": 0,
            "Sb": 0,
            "Te": 0,
            "I": 0,
            "Cs": 0,
            "Ba": 0,
            "La": 0,
            "Ce": 0,
            "Pr": 0,
            "Nd": 0,
            "Sm": 0,
            "Gd": 0,
            "Dy": 0,
            "Er": 0,
            "Yb": 0,
            "Hf": 0,
            "Ta": 0,
            "W": 0,
            "Re": 0,
            "Os": 0,
            "Ir": 0,
            "Pt": 0,
            "Au": 0,
            "Hg": 0,
            "Tl": 0,
            "Pb": 0,
            "Bi": 0,
            "Th": 0,
            "U": 0
        },
        "Ga": {
            "Ga": 0,
            "Ge": 0,
            "As": 0,
            "Se": 0,
            "Br": 0,
            "Rb": 0,
            "Sr": 0,
            "Y": 0,
            "Zr": 0,
            "Nb": 0,
            "Mo": 0,
            "Ru": 0,
            "Rh": 0,
            "Pd": 0,
            "Ag": 0,
            "Cd": 0,
            "In": 0,
            "Sn": 0,
            "Sb": 0,
            "Te": 0,
            "I": 0,
            "Cs": 0,
            "Ba": 0,
            "La": 0,
            "Ce": 0,
            "Pr": 0,
            "Nd": 0,
            "Sm": 0,
            "Gd": 0,
            "Dy": 0,
            "Er": 0,
            "Yb": 0,
            "Hf": 0,
            "Ta": 0,
            "W": 0,
            "Re": 0,
            "Os": 0,
            "Ir": 0,
            "Pt": 0,
            "Au": 0,
            "Hg": 0,
            "Tl": 0,
            "Pb": 0,
            "Bi": 0,
            "Th": 0,
            "U": 0
        },
        "Ge": {
            "Ge": 0,
            "As": 0,
            "Se": 0,
            "Br": 0,
            "Rb": 0,
            "Sr": 0,
            "Y": 0,
            "Zr": 0,
            "Nb": 0,
            "Mo": 0,
            "Ru": 0,
            "Rh": 0,
            "Pd": 0,
            "Ag": 0,
            "Cd": 0,
            "In": 0,
            "Sn": 0,
            "Sb": 0,
            "Te": 0,
            "I": 0,
            "Cs": 0,
            "Ba": 0,
            "La": 0,
            "Ce": 0,
            "Pr": 0,
            "Nd": 0,
            "Sm": 0,
            "Gd": 0,
            "Dy": 0,
            "Er": 0,
            "Yb": 0,
            "Hf": 0,
            "Ta": 0,
            "W": 0,
            "Re": 0,
            "Os": 0,
            "Ir": 0,
            "Pt": 0,
            "Au": 0,
            "Hg": 0,
            "Tl": 0,
            "Pb": 0,
            "Bi": 0,
            "Th": 0,
            "U": 0
        },
        "As": {
            "As": 21,
            "Se": 0,
            "Br": 0,
            "Rb": 0,
            "Sr": 0,
            "Y": 0,
            "Zr": 0,
            "Nb": 0,
            "Mo": 1,
            "Ru": 0,
            "Rh": 0,
            "Pd": 0,
            "Ag": 0,
            "Cd": 0,
            "In": 0,
            "Sn": 0,
            "Sb": 1,
            "Te": 0,
            "I": 0,
            "Cs": 0,
            "Ba": 0,
            "La": 0,
            "Ce": 0,
            "Pr": 0,
            "Nd": 0,
            "Sm": 0,
            "Gd": 0,
            "Dy": 0,
            "Er": 0,
            "Yb": 0,
            "Hf": 0,
            "Ta": 0,
            "W": 0,
            "Re": 0,
            "Os": 0,
            "Ir": 0,
            "Pt": 0,
            "Au": 0,
            "Hg": 0,
            "Tl": 0,
            "Pb": 3,
            "Bi": 21,
            "Th": 0,
            "U": 4
        },
        "Se": {
            "Se": 25,
            "Br": 0,
            "Rb": 0,
            "Sr": 0,
            "Y": 0,
            "Zr": 0,
            "Nb": 0,
            "Mo": 0,
            "Ru": 0,
            "Rh": 0,
            "Pd": 2,
            "Ag": 3,
            "Cd": 0,
            "In": 0,
            "Sn": 0,
            "Sb": 0,
            "Te": 4,
            "I": 0,
            "Cs": 0,
            "Ba": 0,
            "La": 0,
            "Ce": 0,
            "Pr": 0,
            "Nd": 0,
            "Sm": 0,
            "Gd": 0,
            "Dy": 0,
            "Er": 0,
            "Yb": 0,
            "Hf": 0,
            "Ta": 0,
            "W": 0,
            "Re": 0,
            "Os": 0,
            "Ir": 0,
            "Pt": 0,
            "Au": 0,
            "Hg": 2,
            "Tl": 0,
            "Pb": 10,
            "Bi": 25,
            "Th": 0,
            "U": 0
        },
        "Br": {
            "Br": 1,
            "Rb": 0,
            "Sr": 0,
            "Y": 0,
            "Zr": 0,
            "Nb": 0,
            "Mo": 0,
            "Ru": 0,
            "Rh": 0,
            "Pd": 0,
            "Ag": 0,
            "Cd": 0,
            "In": 0,
            "Sn": 0,
            "Sb": 0,
            "Te": 0,
            "I": 0,
            "Cs": 0,
            "Ba": 0,
            "La": 0,
            "Ce": 0,
            "Pr": 0,
            "Nd": 0,
            "Sm": 0,
            "Gd": 0,
            "Dy": 0,
            "Er": 0,
            "Yb": 0,
            "Hf": 0,
            "Ta": 0,
            "W": 0,
            "Re": 0,
            "Os": 0,
            "Ir": 0,
            "Pt": 0,
            "Au": 0,
            "Hg": 0,
            "Tl": 0,
            "Pb": 0,
            "Bi": 1,
            "Th": 0,
            "U": 0
        },
        "Rb": {
            "Rb": 0,
            "Sr": 0,
            "Y": 0,
            "Zr": 0,
            "Nb": 0,
            "Mo": 0,
            "Ru": 0,
            "Rh": 0,
            "Pd": 0,
            "Ag": 0,
            "Cd": 0,
            "In": 0,
            "Sn": 0,
            "Sb": 0,
            "Te": 0,
            "I": 0,
            "Cs": 0,
            "Ba": 0,
            "La": 0,
            "Ce": 0,
            "Pr": 0,
            "Nd": 0,
            "Sm": 0,
            "Gd": 0,
            "Dy": 0,
            "Er": 0,
            "Yb": 0,
            "Hf": 0,
            "Ta": 0,
            "W": 0,
            "Re": 0,
            "Os": 0,
            "Ir": 0,
            "Pt": 0,
            "Au": 0,
            "Hg": 0,
            "Tl": 0,
            "Pb": 0,
            "Bi": 0,
            "Th": 0,
            "U": 0
        },
        "Sr": {
            "Sr": 0,
            "Y": 0,
            "Zr": 0,
            "Nb": 0,
            "Mo": 0,
            "Ru": 0,
            "Rh": 0,
            "Pd": 0,
            "Ag": 0,
            "Cd": 0,
            "In": 0,
            "Sn": 0,
            "Sb": 0,
            "Te": 0,
            "I": 0,
            "Cs": 0,
            "Ba": 0,
            "La": 0,
            "Ce": 0,
            "Pr": 0,
            "Nd": 0,
            "Sm": 0,
            "Gd": 0,
            "Dy": 0,
            "Er": 0,
            "Yb": 0,
            "Hf": 0,
            "Ta": 0,
            "W": 0,
            "Re": 0,
            "Os": 0,
            "Ir": 0,
            "Pt": 0,
            "Au": 0,
            "Hg": 0,
            "Tl": 0,
            "Pb": 0,
            "Bi": 0,
            "Th": 0,
            "U": 0
        },
        "Y": {
            "Y": 0,
            "Zr": 0,
            "Nb": 0,
            "Mo": 0,
            "Ru": 0,
            "Rh": 0,
            "Pd": 0,
            "Ag": 0,
            "Cd": 0,
            "In": 0,
            "Sn": 0,
            "Sb": 0,
            "Te": 0,
            "I": 0,
            "Cs": 0,
            "Ba": 0,
            "La": 0,
            "Ce": 0,
            "Pr": 0,
            "Nd": 0,
            "Sm": 0,
            "Gd": 0,
            "Dy": 0,
            "Er": 0,
            "Yb": 0,
            "Hf": 0,
            "Ta": 0,
            "W": 0,
            "Re": 0,
            "Os": 0,
            "Ir": 0,
            "Pt": 0,
            "Au": 0,
            "Hg": 0,
            "Tl": 0,
            "Pb": 0,
            "Bi": 0,
            "Th": 0,
            "U": 0
        },
        "Zr": {
            "Zr": 0,
            "Nb": 0,
            "Mo": 0,
            "Ru": 0,
            "Rh": 0,
            "Pd": 0,
            "Ag": 0,
            "Cd": 0,
            "In": 0,
            "Sn": 0,
            "Sb": 0,
            "Te": 0,
            "I": 0,
            "Cs": 0,
            "Ba": 0,
            "La": 0,
            "Ce": 0,
            "Pr": 0,
            "Nd": 0,
            "Sm": 0,
            "Gd": 0,
            "Dy": 0,
            "Er": 0,
            "Yb": 0,
            "Hf": 0,
            "Ta": 0,
            "W": 0,
            "Re": 0,
            "Os": 0,
            "Ir": 0,
            "Pt": 0,
            "Au": 0,
            "Hg": 0,
            "Tl": 0,
            "Pb": 0,
            "Bi": 0,
            "Th": 0,
            "U": 0
        },
        "Nb": {
            "Nb": 1,
            "Mo": 0,
            "Ru": 0,
            "Rh": 0,
            "Pd": 0,
            "Ag": 0,
            "Cd": 0,
            "In": 0,
            "Sn": 0,
            "Sb": 0,
            "Te": 0,
            "I": 0,
            "Cs": 0,
            "Ba": 0,
            "La": 0,
            "Ce": 0,
            "Pr": 0,
            "Nd": 0,
            "Sm": 0,
            "Gd": 0,
            "Dy": 0,
            "Er": 0,
            "Yb": 0,
            "Hf": 0,
            "Ta": 0,
            "W": 0,
            "Re": 0,
            "Os": 0,
            "Ir": 0,
            "Pt": 0,
            "Au": 0,
            "Hg": 0,
            "Tl": 0,
            "Pb": 0,
            "Bi": 1,
            "Th": 0,
            "U": 0
        },
        "Mo": {
            "Mo": 7,
            "Ru": 0,
            "Rh": 0,
            "Pd": 0,
            "Ag": 0,
            "Cd": 0,
            "In": 0,
            "Sn": 0,
            "Sb": 0,
            "Te": 1,
            "I": 0,
            "Cs": 0,
            "Ba": 0,
            "La": 0,
            "Ce": 0,
            "Pr": 0,
            "Nd": 0,
            "Sm": 0,
            "Gd": 0,
            "Dy": 0,
            "Er": 0,
            "Yb": 0,
            "Hf": 0,
            "Ta": 0,
            "W": 0,
            "Re": 0,
            "Os": 0,
            "Ir": 0,
            "Pt": 0,
            "Au": 0,
            "Hg": 0,
            "Tl": 0,
            "Pb": 0,
            "Bi": 7,
            "Th": 0,
            "U": 0
        },
        "Ru": {
            "Ru": 0,
            "Rh": 0,
            "Pd": 0,
            "Ag": 0,
            "Cd": 0,
            "In": 0,
            "Sn": 0,
            "Sb": 0,
            "Te": 0,
            "I": 0,
            "Cs": 0,
            "Ba": 0,
            "La": 0,
            "Ce": 0,
            "Pr": 0,
            "Nd": 0,
            "Sm": 0,
            "Gd": 0,
            "Dy": 0,
            "Er": 0,
            "Yb": 0,
            "Hf": 0,
            "Ta": 0,
            "W": 0,
            "Re": 0,
            "Os": 0,
            "Ir": 0,
            "Pt": 0,
            "Au": 0,
            "Hg": 0,
            "Tl": 0,
            "Pb": 0,
            "Bi": 0,
            "Th": 0,
            "U": 0
        },
        "Rh": {
            "Rh": 0,
            "Pd": 0,
            "Ag": 0,
            "Cd": 0,
            "In": 0,
            "Sn": 0,
            "Sb": 0,
            "Te": 0,
            "I": 0,
            "Cs": 0,
            "Ba": 0,
            "La": 0,
            "Ce": 0,
            "Pr": 0,
            "Nd": 0,
            "Sm": 0,
            "Gd": 0,
            "Dy": 0,
            "Er": 0,
            "Yb": 0,
            "Hf": 0,
            "Ta": 0,
            "W": 0,
            "Re": 0,
            "Os": 0,
            "Ir": 0,
            "Pt": 0,
            "Au": 0,
            "Hg": 0,
            "Tl": 0,
            "Pb": 0,
            "Bi": 0,
            "Th": 0,
            "U": 0
        },
        "Pd": {
            "Pd": 10,
            "Ag": 1,
            "Cd": 0,
            "In": 0,
            "Sn": 0,
            "Sb": 0,
            "Te": 1,
            "I": 0,
            "Cs": 0,
            "Ba": 0,
            "La": 0,
            "Ce": 0,
            "Pr": 0,
            "Nd": 0,
            "Sm": 0,
            "Gd": 0,
            "Dy": 0,
            "Er": 0,
            "Yb": 0,
            "Hf": 0,
            "Ta": 0,
            "W": 0,
            "Re": 0,
            "Os": 0,
            "Ir": 0,
            "Pt": 0,
            "Au": 0,
            "Hg": 0,
            "Tl": 0,
            "Pb": 0,
            "Bi": 10,
            "Th": 0,
            "U": 0
        },
        "Ag": {
            "Ag": 32,
            "Cd": 0,
            "In": 0,
            "Sn": 0,
            "Sb": 5,
            "Te": 1,
            "I": 0,
            "Cs": 0,
            "Ba": 0,
            "La": 0,
            "Ce": 0,
            "Pr": 0,
            "Nd": 0,
            "Sm": 0,
            "Gd": 0,
            "Dy": 0,
            "Er": 0,
            "Yb": 0,
            "Hf": 0,
            "Ta": 0,
            "W": 0,
            "Re": 0,
            "Os": 0,
            "Ir": 0,
            "Pt": 0,
            "Au": 0,
            "Hg": 0,
            "Tl": 0,
            "Pb": 21,
            "Bi": 32,
            "Th": 0,
            "U": 0
        },
        "Cd": {
            "Cd": 1,
            "In": 0,
            "Sn": 0,
            "Sb": 0,
            "Te": 0,
            "I": 0,
            "Cs": 0,
            "Ba": 0,
            "La": 0,
            "Ce": 0,
            "Pr": 0,
            "Nd": 0,
            "Sm": 0,
            "Gd": 0,
            "Dy": 0,
            "Er": 0,
            "Yb": 0,
            "Hf": 0,
            "Ta": 0,
            "W": 0,
            "Re": 0,
            "Os": 0,
            "Ir": 0,
            "Pt": 0,
            "Au": 0,
            "Hg": 0,
            "Tl": 0,
            "Pb": 0,
            "Bi": 1,
            "Th": 0,
            "U": 0
        },
        "In": {
            "In": 2,
            "Sn": 1,
            "Sb": 0,
            "Te": 0,
            "I": 0,
            "Cs": 0,
            "Ba": 0,
            "La": 0,
            "Ce": 0,
            "Pr": 0,
            "Nd": 0,
            "Sm": 0,
            "Gd": 0,
            "Dy": 0,
            "Er": 0,
            "Yb": 0,
            "Hf": 0,
            "Ta": 0,
            "W": 0,
            "Re": 0,
            "Os": 0,
            "Ir": 0,
            "Pt": 0,
            "Au": 0,
            "Hg": 0,
            "Tl": 0,
            "Pb": 2,
            "Bi": 2,
            "Th": 0,
            "U": 0
        },
        "Sn": {
            "Sn": 3,
            "Sb": 0,
            "Te": 0,
            "I": 0,
            "Cs": 0,
            "Ba": 0,
            "La": 0,
            "Ce": 0,
            "Pr": 0,
            "Nd": 0,
            "Sm": 0,
            "Gd": 0,
            "Dy": 0,
            "Er": 0,
            "Yb": 0,
            "Hf": 0,
            "Ta": 0,
            "W": 0,
            "Re": 0,
            "Os": 0,
            "Ir": 0,
            "Pt": 0,
            "Au": 0,
            "Hg": 0,
            "Tl": 0,
            "Pb": 3,
            "Bi": 3,
            "Th": 0,
            "U": 0
        },
        "Sb": {
            "Sb": 10,
            "Te": 0,
            "I": 0,
            "Cs": 0,
            "Ba": 0,
            "La": 0,
            "Ce": 0,
            "Pr": 0,
            "Nd": 0,
            "Sm": 0,
            "Gd": 0,
            "Dy": 0,
            "Er": 0,
            "Yb": 0,
            "Hf": 0,
            "Ta": 0,
            "W": 0,
            "Re": 0,
            "Os": 0,
            "Ir": 0,
            "Pt": 0,
            "Au": 0,
            "Hg": 0,
            "Tl": 0,
            "Pb": 5,
            "Bi": 10,
            "Th": 0,
            "U": 0
        },
        "Te": {
            "Te": 33,
            "I": 0,
            "Cs": 0,
            "Ba": 0,
            "La": 0,
            "Ce": 0,
            "Pr": 0,
            "Nd": 0,
            "Sm": 0,
            "Gd": 0,
            "Dy": 0,
            "Er": 0,
            "Yb": 0,
            "Hf": 0,
            "Ta": 0,
            "W": 0,
            "Re": 0,
            "Os": 0,
            "Ir": 1,
            "Pt": 1,
            "Au": 1,
            "Hg": 0,
            "Tl": 0,
            "Pb": 6,
            "Bi": 33,
            "Th": 0,
            "U": 0
        },
        "I": {
            "I": 1,
            "Cs": 0,
            "Ba": 0,
            "La": 0,
            "Ce": 0,
            "Pr": 0,
            "Nd": 0,
            "Sm": 0,
            "Gd": 0,
            "Dy": 0,
            "Er": 0,
            "Yb": 0,
            "Hf": 0,
            "Ta": 0,
            "W": 0,
            "Re": 0,
            "Os": 0,
            "Ir": 0,
            "Pt": 0,
            "Au": 0,
            "Hg": 0,
            "Tl": 0,
            "Pb": 0,
            "Bi": 1,
            "Th": 0,
            "U": 0
        },
        "Cs": {
            "Cs": 0,
            "Ba": 0,
            "La": 0,
            "Ce": 0,
            "Pr": 0,
            "Nd": 0,
            "Sm": 0,
            "Gd": 0,
            "Dy": 0,
            "Er": 0,
            "Yb": 0,
            "Hf": 0,
            "Ta": 0,
            "W": 0,
            "Re": 0,
            "Os": 0,
            "Ir": 0,
            "Pt": 0,
            "Au": 0,
            "Hg": 0,
            "Tl": 0,
            "Pb": 0,
            "Bi": 0,
            "Th": 0,
            "U": 0
        },
        "Ba": {
            "Ba": 0,
            "La": 0,
            "Ce": 0,
            "Pr": 0,
            "Nd": 0,
            "Sm": 0,
            "Gd": 0,
            "Dy": 0,
            "Er": 0,
            "Yb": 0,
            "Hf": 0,
            "Ta": 0,
            "W": 0,
            "Re": 0,
            "Os": 0,
            "Ir": 0,
            "Pt": 0,
            "Au": 0,
            "Hg": 0,
            "Tl": 0,
            "Pb": 0,
            "Bi": 0,
            "Th": 0,
            "U": 0
        },
        "La": {
            "La": 0,
            "Ce": 0,
            "Pr": 0,
            "Nd": 0,
            "Sm": 0,
            "Gd": 0,
            "Dy": 0,
            "Er": 0,
            "Yb": 0,
            "Hf": 0,
            "Ta": 0,
            "W": 0,
            "Re": 0,
            "Os": 0,
            "Ir": 0,
            "Pt": 0,
            "Au": 0,
            "Hg": 0,
            "Tl": 0,
            "Pb": 0,
            "Bi": 0,
            "Th": 0,
            "U": 0
        },
        "Ce": {
            "Ce": 0,
            "Pr": 0,
            "Nd": 0,
            "Sm": 0,
            "Gd": 0,
            "Dy": 0,
            "Er": 0,
            "Yb": 0,
            "Hf": 0,
            "Ta": 0,
            "W": 0,
            "Re": 0,
            "Os": 0,
            "Ir": 0,
            "Pt": 0,
            "Au": 0,
            "Hg": 0,
            "Tl": 0,
            "Pb": 0,
            "Bi": 0,
            "Th": 0,
            "U": 0
        },
        "Pr": {
            "Pr": 0,
            "Nd": 0,
            "Sm": 0,
            "Gd": 0,
            "Dy": 0,
            "Er": 0,
            "Yb": 0,
            "Hf": 0,
            "Ta": 0,
            "W": 0,
            "Re": 0,
            "Os": 0,
            "Ir": 0,
            "Pt": 0,
            "Au": 0,
            "Hg": 0,
            "Tl": 0,
            "Pb": 0,
            "Bi": 0,
            "Th": 0,
            "U": 0
        },
        "Nd": {
            "Nd": 0,
            "Sm": 0,
            "Gd": 0,
            "Dy": 0,
            "Er": 0,
            "Yb": 0,
            "Hf": 0,
            "Ta": 0,
            "W": 0,
            "Re": 0,
            "Os": 0,
            "Ir": 0,
            "Pt": 0,
            "Au": 0,
            "Hg": 0,
            "Tl": 0,
            "Pb": 0,
            "Bi": 0,
            "Th": 0,
            "U": 0
        },
        "Sm": {
            "Sm": 0,
            "Gd": 0,
            "Dy": 0,
            "Er": 0,
            "Yb": 0,
            "Hf": 0,
            "Ta": 0,
            "W": 0,
            "Re": 0,
            "Os": 0,
            "Ir": 0,
            "Pt": 0,
            "Au": 0,
            "Hg": 0,
            "Tl": 0,
            "Pb": 0,
            "Bi": 0,
            "Th": 0,
            "U": 0
        },
        "Gd": {
            "Gd": 0,
            "Dy": 0,
            "Er": 0,
            "Yb": 0,
            "Hf": 0,
            "Ta": 0,
            "W": 0,
            "Re": 0,
            "Os": 0,
            "Ir": 0,
            "Pt": 0,
            "Au": 0,
            "Hg": 0,
            "Tl": 0,
            "Pb": 0,
            "Bi": 0,
            "Th": 0,
            "U": 0
        },
        "Dy": {
            "Dy": 0,
            "Er": 0,
            "Yb": 0,
            "Hf": 0,
            "Ta": 0,
            "W": 0,
            "Re": 0,
            "Os": 0,
            "Ir": 0,
            "Pt": 0,
            "Au": 0,
            "Hg": 0,
            "Tl": 0,
            "Pb": 0,
            "Bi": 0,
            "Th": 0,
            "U": 0
        },
        "Er": {
            "Er": 0,
            "Yb": 0,
            "Hf": 0,
            "Ta": 0,
            "W": 0,
            "Re": 0,
            "Os": 0,
            "Ir": 0,
            "Pt": 0,
            "Au": 0,
            "Hg": 0,
            "Tl": 0,
            "Pb": 0,
            "Bi": 0,
            "Th": 0,
            "U": 0
        },
        "Yb": {
            "Yb": 0,
            "Hf": 0,
            "Ta": 0,
            "W": 0,
            "Re": 0,
            "Os": 0,
            "Ir": 0,
            "Pt": 0,
            "Au": 0,
            "Hg": 0,
            "Tl": 0,
            "Pb": 0,
            "Bi": 0,
            "Th": 0,
            "U": 0
        },
        "Hf": {
            "Hf": 0,
            "Ta": 0,
            "W": 0,
            "Re": 0,
            "Os": 0,
            "Ir": 0,
            "Pt": 0,
            "Au": 0,
            "Hg": 0,
            "Tl": 0,
            "Pb": 0,
            "Bi": 0,
            "Th": 0,
            "U": 0
        },
        "Ta": {
            "Ta": 3,
            "W": 0,
            "Re": 0,
            "Os": 0,
            "Ir": 0,
            "Pt": 0,
            "Au": 0,
            "Hg": 0,
            "Tl": 0,
            "Pb": 0,
            "Bi": 3,
            "Th": 0,
            "U": 0
        },
        "W": {
            "W": 1,
            "Re": 0,
            "Os": 0,
            "Ir": 0,
            "Pt": 0,
            "Au": 0,
            "Hg": 0,
            "Tl": 0,
            "Pb": 0,
            "Bi": 1,
            "Th": 0,
            "U": 0
        },
        "Re": {
            "Re": 0,
            "Os": 0,
            "Ir": 0,
            "Pt": 0,
            "Au": 0,
            "Hg": 0,
            "Tl": 0,
            "Pb": 0,
            "Bi": 0,
            "Th": 0,
            "U": 0
        },
        "Os": {
            "Os": 0,
            "Ir": 0,
            "Pt": 0,
            "Au": 0,
            "Hg": 0,
            "Tl": 0,
            "Pb": 0,
            "Bi": 0,
            "Th": 0,
            "U": 0
        },
        "Ir": {
            "Ir": 2,
            "Pt": 0,
            "Au": 0,
            "Hg": 0,
            "Tl": 0,
            "Pb": 0,
            "Bi": 2,
            "Th": 0,
            "U": 0
        },
        "Pt": {
            "Pt": 5,
            "Au": 0,
            "Hg": 0,
            "Tl": 0,
            "Pb": 0,
            "Bi": 5,
            "Th": 0,
            "U": 0
        },
        "Au": {
            "Au": 4,
            "Hg": 0,
            "Tl": 0,
            "Pb": 1,
            "Bi": 4,
            "Th": 0,
            "U": 0
        },
        "Hg": {
            "Hg": 3,
            "Tl": 0,
            "Pb": 2,
            "Bi": 3,
            "Th": 0,
            "U": 0
        },
        "Tl": {
            "Tl": 2,
            "Pb": 0,
            "Bi": 2,
            "Th": 0,
            "U": 0
        },
        "Pb": {
            "Pb": 77,
            "Bi": 77,
            "Th": 0,
            "U": 2
        },
        "Bi": {
            "Bi": 231,
            "Th": 0,
            "U": 7
        },
        "Th": {
            "Th": 0,
            "U": 0
        },
        "U": {
            "U": 7
        }
    }
}