{
    "with": {
        "H": {
            "H": 230,
            "B": 5,
            "C": 28,
            "O": 229,
            "F": 6,
            "Na": 3,
            "Mg": 7,
            "Al": 27,
            "Si": 33,
            "P": 27,
            "S": 54,
            "Cl": 39,
            "K": 3,
            "Ca": 13,
            "Ti": 1,
            "V": 14,
            "Mn": 19,
            "Fe": 36,
            "Ni": 1,
            "Cu": 59,
            "Zn": 26,
            "As": 48,
            "Se": 8,
            "Ag": 2,
            "Sb": 4,
            "Ba": 2,
            "Pb": 230,
            "Bi": 4,
            "U": 28,
            "REE": 3
        },
        "B": {
            "B": 6,
            "C": 3,
            "O": 6,
            "F": 2,
            "Na": 0,
            "Mg": 2,
            "Al": 0,
            "Si": 3,
            "P": 0,
            "S": 0,
            "Cl": 3,
            "K": 0,
            "Ca": 1,
            "Ti": 0,
            "V": 0,
            "Mn": 1,
            "Fe": 0,
            "Ni": 0,
            "Cu": 0,
            "Zn": 0,
            "As": 0,
            "Se": 0,
            "Ag": 0,
            "Sb": 0,
            "Ba": 0,
            "Pb": 6,
            "Bi": 0,
            "U": 0,
            "REE": 0
        },
        "C": {
            "C": 35,
            "O": 35,
            "F": 1,
            "Na": 2,
            "Mg": 4,
            "Al": 4,
            "Si": 8,
            "P": 0,
            "S": 8,
            "Cl": 7,
            "K": 0,
            "Ca": 1,
            "Ti": 0,
            "V": 0,
            "Mn": 2,
            "Fe": 1,
            "Ni": 0,
            "Cu": 5,
            "Zn": 0,
            "As": 0,
            "Se": 0,
            "Ag": 0,
            "Sb": 0,
            "Ba": 0,
            "Pb": 35,
            "Bi": 0,
            "U": 1,
            "REE": 3
        },
        "O": {
            "O": 358,
            "F": 13,
            "Na": 6,
            "Mg": 7,
            "Al": 29,
            "Si": 50,
            "P": 33,
            "S": 76,
            "Cl": 82,
            "K": 6,
            "Ca": 23,
            "Ti": 5,
            "V": 23,
            "Mn": 31,
            "Fe": 54,
            "Ni": 1,
            "Cu": 70,
            "Zn": 34,
            "As": 62,
            "Se": 14,
            "Ag": 3,
            "Sb": 14,
            "Ba": 2,
            "Pb": 358,
            "Bi": 5,
            "U": 32,
            "REE": 4
        },
        "F": {
            "F": 19,
            "Na": 0,
            "Mg": 1,
            "Al": 4,
            "Si": 2,
            "P": 2,
            "S": 3,
            "Cl": 8,
            "K": 0,
            "Ca": 4,
            "Ti": 0,
            "V": 0,
            "Mn": 0,
            "Fe": 0,
            "Ni": 0,
            "Cu": 0,
            "Zn": 0,
            "As": 0,
            "Se": 0,
            "Ag": 1,
            "Sb": 0,
            "Ba": 0,
            "Pb": 19,
            "Bi": 0,
            "U": 0,
            "REE": 0
        },
        "Na": {
            "Na": 6,
            "Mg": 0,
            "Al": 1,
            "Si": 0,
            "P": 1,
            "S": 1,
            "Cl": 2,
            "K": 0,
            "Ca": 2,
            "Ti": 0,
            "V": 0,
            "Mn": 0,
            "Fe": 1,
            "Ni": 0,
            "Cu": 1,
            "Zn": 0,
            "As": 2,
            "Se": 0,
            "Ag": 0,
            "Sb": 0,
            "Ba": 0,
            "Pb": 6,
            "Bi": 0,
            "U": 0,
            "REE": 0
        },
        "Mg": {
            "Mg": 7,
            "Al": 0,
            "Si": 4,
            "P": 0,
            "S": 1,
            "Cl": 2,
            "K": 0,
            "Ca": 1,
            "Ti": 0,
            "V": 0,
            "Mn": 2,
            "Fe": 1,
            "Ni": 0,
            "Cu": 0,
            "Zn": 0,
            "As": 1,
            "Se": 0,
            "Ag": 0,
            "Sb": 0,
            "Ba": 0,
            "Pb": 7,
            "Bi": 0,
            "U": 0,
            "REE": 0
        },
        "Al": {
            "Al": 31,
            "Si": 12,
            "P": 5,
            "S": 8,
            "Cl": 4,
            "K": 0,
            "Ca": 8,
            "Ti": 0,
            "V": 1,
            "Mn": 2,
            "Fe": 5,
            "Ni": 0,
            "Cu": 5,
            "Zn": 0,
            "As": 4,
            "Se": 0,
            "Ag": 0,
            "Sb": 1,
            "Ba": 0,
            "Pb": 31,
            "Bi": 0,
            "U": 1,
            "REE": 0
        },
        "Si": {
            "Si": 50,
            "P": 0,
            "S": 7,
            "Cl": 9,
            "K": 0,
            "Ca": 15,
            "Ti": 0,
            "V": 0,
            "Mn": 8,
            "Fe": 10,
            "Ni": 0,
            "Cu": 7,
            "Zn": 5,
            "As": 2,
            "Se": 0,
            "Ag": 0,
            "Sb": 0,
            "Ba": 1,
            "Pb": 50,
            "Bi": 0,
            "U": 2,
            "REE": 0
        },
        "P": {
            "P": 33,
            "S": 3,
            "Cl": 2,
            "K": 0,
            "Ca": 3,
            "Ti": 0,
            "V": 2,
            "Mn": 1,
            "Fe": 9,
            "Ni": 0,
            "Cu": 5,
            "Zn": 5,
            "As": 3,
            "Se": 0,
            "Ag": 0,
            "Sb": 0,
            "Ba": 0,
            "Pb": 33,
            "Bi": 1,
            "U": 7,
            "REE": 0
        },
        "S": {
            "S": 257,
            "Cl": 19,
            "K": 2,
            "Ca": 2,
            "Ti": 0,
            "V": 1,
            "Mn": 10,
            "Fe": 15,
            "Ni": 2,
            "Cu": 73,
            "Zn": 10,
            "As": 60,
            "Se": 5,
            "Ag": 57,
            "Sb": 85,
            "Ba": 0,
            "Pb": 257,
            "Bi": 63,
            "U": 0,
            "REE": 0
        },
        "Cl": {
            "Cl": 99,
            "K": 4,
            "Ca": 4,
            "Ti": 0,
            "V": 5,
            "Mn": 4,
            "Fe": 6,
            "Ni": 0,
            "Cu": 21,
            "Zn": 2,
            "As": 16,
            "Se": 4,
            "Ag": 3,
            "Sb": 8,
            "Ba": 1,
            "Pb": 99,
            "Bi": 2,
            "U": 0,
            "REE": 0
        },
        "K": {
            "K": 8,
            "Ca": 0,
            "Ti": 0,
            "V": 0,
            "Mn": 0,
            "Fe": 0,
            "Ni": 0,
            "Cu": 3,
            "Zn": 1,
            "As": 0,
            "Se": 1,
            "Ag": 1,
            "Sb": 0,
            "Ba": 0,
            "Pb": 8,
            "Bi": 0,
            "U": 2,
            "REE": 0
        },
        "Ca": {
            "Ca": 25,
            "Ti": 0,
            "V": 1,
            "Mn": 4,
            "Fe": 4,
            "Ni": 0,
            "Cu": 1,
            "Zn": 1,
            "As": 3,
            "Se": 1,
            "Ag": 0,
            "Sb": 0,
            "Ba": 1,
            "Pb": 25,
            "Bi": 0,
            "U": 0,
            "REE": 0
        },
        "Ti": {
            "Ti": 5,
            "V": 0,
            "Mn": 2,
            "Fe": 3,
            "Ni": 0,
            "Cu": 0,
            "Zn": 1,
            "As": 0,
            "Se": 0,
            "Ag": 0,
            "Sb": 0,
            "Ba": 0,
            "Pb": 5,
            "Bi": 0,
            "U": 1,
            "REE": 1
        },
        "V": {
            "V": 24,
            "Mn": 4,
            "Fe": 5,
            "Ni": 0,
            "Cu": 2,
            "Zn": 2,
            "As": 1,
            "Se": 0,
            "Ag": 0,
            "Sb": 1,
            "Ba": 0,
            "Pb": 24,
            "Bi": 1,
            "U": 1,
            "REE": 0
        },
        "Mn": {
            "Mn": 38,
            "Fe": 9,
            "Ni": 0,
            "Cu": 0,
            "Zn": 3,
            "As": 7,
            "Se": 0,
            "Ag": 4,
            "Sb": 7,
            "Ba": 1,
            "Pb": 38,
            "Bi": 0,
            "U": 0,
            "REE": 0
        },
        "Fe": {
            "Fe": 63,
            "Ni": 0,
            "Cu": 5,
            "Zn": 4,
            "As": 14,
            "Se": 0,
            "Ag": 2,
            "Sb": 7,
            "Ba": 2,
            "Pb": 63,
            "Bi": 1,
            "U": 3,
            "REE": 1
        },
        "Ni": {
            "Ni": 3,
            "Cu": 0,
            "Zn": 0,
            "As": 1,
            "Se": 0,
            "Ag": 0,
            "Sb": 1,
            "Ba": 0,
            "Pb": 3,
            "Bi": 0,
            "U": 0,
            "REE": 0
        },
        "Cu": {
            "Cu": 128,
            "Zn": 5,
            "As": 18,
            "Se": 16,
            "Ag": 14,
            "Sb": 14,
            "Ba": 0,
            "Pb": 128,
            "Bi": 39,
            "U": 1,
            "REE": 1
        },
        "Zn": {
            "Zn": 34,
            "As": 12,
            "Se": 1,
            "Ag": 1,
            "Sb": 1,
            "Ba": 0,
            "Pb": 34,
            "Bi": 0,
            "U": 0,
            "REE": 0
        },
        "As": {
            "As": 117,
            "Se": 0,
            "Ag": 19,
            "Sb": 27,
            "Ba": 0,
            "Pb": 117,
            "Bi": 3,
            "U": 4,
            "REE": 0
        },
        "Se": {
            "Se": 25,
            "Ag": 2,
            "Sb": 0,
            "Ba": 0,
            "Pb": 25,
            "Bi": 10,
            "U": 2,
            "REE": 0
        },
        "Ag": {
            "Ag": 63,
            "Sb": 33,
            "Ba": 0,
            "Pb": 63,
            "Bi": 21,
            "U": 0,
            "REE": 0
        },
        "Sb": {
            "Sb": 93,
            "Ba": 0,
            "Pb": 93,
            "Bi": 5,
            "U": 0,
            "REE": 0
        },
        "Ba": {
            "Ba": 2,
            "Pb": 2,
            "Bi": 0,
            "U": 1,
            "REE": 0
        },
        "Pb": {
            "Pb": 577,
            "Bi": 77,
            "U": 32,
            "REE": 4
        },
        "Bi": {
            "Bi": 77,
            "U": 2,
            "REE": 0
        },
        "U": {
            "U": 32,
            "REE": 0
        },
        "REE": {
            "REE": 4
        }
    }
}