{
    "with": {
        "H": {
            "H": 795,
            "B": 20,
            "C": 23,
            "O": 795,
            "F": 49,
            "Na": 173,
            "Mg": 160,
            "Al": 215,
            "Si": 280,
            "P": 196,
            "S": 134,
            "Cl": 48,
            "K": 100,
            "Ca": 228,
            "Ti": 82,
            "V": 29,
            "Mn": 154,
            "Fe": 795,
            "Ni": 10,
            "Cu": 33,
            "Zn": 62,
            "As": 100,
            "Se": 1,
            "Ag": 1,
            "Sb": 8,
            "Ba": 47,
            "Pb": 46,
            "Bi": 11,
            "U": 20,
            "REE": 49
        },
        "B": {
            "B": 52,
            "C": 0,
            "O": 52,
            "F": 8,
            "Na": 12,
            "Mg": 26,
            "Al": 26,
            "Si": 31,
            "P": 2,
            "S": 2,
            "Cl": 6,
            "K": 0,
            "Ca": 18,
            "Ti": 5,
            "V": 0,
            "Mn": 8,
            "Fe": 52,
            "Ni": 1,
            "Cu": 1,
            "Zn": 0,
            "As": 2,
            "Se": 0,
            "Ag": 0,
            "Sb": 2,
            "Ba": 2,
            "Pb": 0,
            "Bi": 0,
            "U": 0,
            "REE": 8
        },
        "C": {
            "C": 36,
            "O": 30,
            "F": 1,
            "Na": 7,
            "Mg": 11,
            "Al": 3,
            "Si": 10,
            "P": 2,
            "S": 4,
            "Cl": 1,
            "K": 1,
            "Ca": 6,
            "Ti": 2,
            "V": 1,
            "Mn": 2,
            "Fe": 36,
            "Ni": 3,
            "Cu": 0,
            "Zn": 2,
            "As": 0,
            "Se": 0,
            "Ag": 0,
            "Sb": 0,
            "Ba": 3,
            "Pb": 2,
            "Bi": 0,
            "U": 0,
            "REE": 3
        },
        "O": {
            "O": 1166,
            "F": 81,
            "Na": 262,
            "Mg": 267,
            "Al": 287,
            "Si": 418,
            "P": 251,
            "S": 149,
            "Cl": 63,
            "K": 131,
            "Ca": 342,
            "Ti": 164,
            "V": 41,
            "Mn": 219,
            "Fe": 1166,
            "Ni": 15,
            "Cu": 55,
            "Zn": 72,
            "As": 128,
            "Se": 1,
            "Ag": 1,
            "Sb": 25,
            "Ba": 66,
            "Pb": 68,
            "Bi": 12,
            "U": 28,
            "REE": 86
        },
        "F": {
            "F": 81,
            "Na": 51,
            "Mg": 27,
            "Al": 25,
            "Si": 61,
            "P": 14,
            "S": 1,
            "Cl": 1,
            "K": 18,
            "Ca": 32,
            "Ti": 29,
            "V": 3,
            "Mn": 19,
            "Fe": 81,
            "Ni": 0,
            "Cu": 0,
            "Zn": 1,
            "As": 4,
            "Se": 0,
            "Ag": 0,
            "Sb": 0,
            "Ba": 16,
            "Pb": 1,
            "Bi": 0,
            "U": 2,
            "REE": 12
        },
        "Na": {
            "Na": 264,
            "Mg": 68,
            "Al": 74,
            "Si": 155,
            "P": 54,
            "S": 19,
            "Cl": 26,
            "K": 54,
            "Ca": 114,
            "Ti": 56,
            "V": 4,
            "Mn": 69,
            "Fe": 264,
            "Ni": 0,
            "Cu": 13,
            "Zn": 3,
            "As": 29,
            "Se": 0,
            "Ag": 0,
            "Sb": 0,
            "Ba": 23,
            "Pb": 4,
            "Bi": 0,
            "U": 2,
            "REE": 15
        },
        "Mg": {
            "Mg": 269,
            "Al": 114,
            "Si": 125,
            "P": 50,
            "S": 21,
            "Cl": 10,
            "K": 32,
            "Ca": 97,
            "Ti": 43,
            "V": 6,
            "Mn": 65,
            "Fe": 269,
            "Ni": 3,
            "Cu": 6,
            "Zn": 19,
            "As": 18,
            "Se": 0,
            "Ag": 0,
            "Sb": 5,
            "Ba": 21,
            "Pb": 6,
            "Bi": 1,
            "U": 2,
            "REE": 8
        },
        "Al": {
            "Al": 293,
            "Si": 162,
            "P": 60,
            "S": 26,
            "Cl": 6,
            "K": 46,
            "Ca": 130,
            "Ti": 33,
            "V": 7,
            "Mn": 52,
            "Fe": 293,
            "Ni": 4,
            "Cu": 10,
            "Zn": 20,
            "As": 14,
            "Se": 0,
            "Ag": 0,
            "Sb": 4,
            "Ba": 15,
            "Pb": 9,
            "Bi": 0,
            "U": 2,
            "REE": 26
        },
        "Si": {
            "Si": 428,
            "P": 7,
            "S": 4,
            "Cl": 32,
            "K": 74,
            "Ca": 190,
            "Ti": 87,
            "V": 5,
            "Mn": 91,
            "Fe": 428,
            "Ni": 2,
            "Cu": 5,
            "Zn": 9,
            "As": 10,
            "Se": 0,
            "Ag": 0,
            "Sb": 4,
            "Ba": 43,
            "Pb": 11,
            "Bi": 1,
            "U": 0,
            "REE": 62
        },
        "P": {
            "P": 262,
            "S": 10,
            "Cl": 2,
            "K": 16,
            "Ca": 83,
            "Ti": 3,
            "V": 2,
            "Mn": 82,
            "Fe": 262,
            "Ni": 9,
            "Cu": 7,
            "Zn": 19,
            "As": 2,
            "Se": 0,
            "Ag": 0,
            "Sb": 0,
            "Ba": 11,
            "Pb": 10,
            "Bi": 4,
            "U": 6,
            "REE": 4
        },
        "S": {
            "S": 275,
            "Cl": 10,
            "K": 32,
            "Ca": 10,
            "Ti": 2,
            "V": 1,
            "Mn": 9,
            "Fe": 275,
            "Ni": 22,
            "Cu": 79,
            "Zn": 27,
            "As": 23,
            "Se": 2,
            "Ag": 22,
            "Sb": 20,
            "Ba": 4,
            "Pb": 27,
            "Bi": 8,
            "U": 7,
            "REE": 0
        },
        "Cl": {
            "Cl": 70,
            "K": 16,
            "Ca": 28,
            "Ti": 7,
            "V": 0,
            "Mn": 13,
            "Fe": 70,
            "Ni": 5,
            "Cu": 8,
            "Zn": 1,
            "As": 5,
            "Se": 0,
            "Ag": 0,
            "Sb": 0,
            "Ba": 7,
            "Pb": 8,
            "Bi": 2,
            "U": 0,
            "REE": 2
        },
        "K": {
            "K": 141,
            "Ca": 32,
            "Ti": 27,
            "V": 3,
            "Mn": 20,
            "Fe": 141,
            "Ni": 2,
            "Cu": 10,
            "Zn": 3,
            "As": 6,
            "Se": 0,
            "Ag": 0,
            "Sb": 0,
            "Ba": 15,
            "Pb": 3,
            "Bi": 1,
            "U": 1,
            "REE": 1
        },
        "Ca": {
            "Ca": 342,
            "Ti": 48,
            "V": 8,
            "Mn": 88,
            "Fe": 342,
            "Ni": 2,
            "Cu": 11,
            "Zn": 10,
            "As": 30,
            "Se": 0,
            "Ag": 0,
            "Sb": 5,
            "Ba": 18,
            "Pb": 8,
            "Bi": 2,
            "U": 4,
            "REE": 41
        },
        "Ti": {
            "Ti": 169,
            "V": 8,
            "Mn": 36,
            "Fe": 169,
            "Ni": 0,
            "Cu": 0,
            "Zn": 11,
            "As": 7,
            "Se": 0,
            "Ag": 0,
            "Sb": 2,
            "Ba": 32,
            "Pb": 8,
            "Bi": 0,
            "U": 10,
            "REE": 33
        },
        "V": {
            "V": 42,
            "Mn": 6,
            "Fe": 42,
            "Ni": 0,
            "Cu": 5,
            "Zn": 1,
            "As": 2,
            "Se": 0,
            "Ag": 0,
            "Sb": 1,
            "Ba": 2,
            "Pb": 7,
            "Bi": 0,
            "U": 4,
            "REE": 5
        },
        "Mn": {
            "Mn": 222,
            "Fe": 222,
            "Ni": 0,
            "Cu": 2,
            "Zn": 28,
            "As": 15,
            "Se": 0,
            "Ag": 1,
            "Sb": 9,
            "Ba": 13,
            "Pb": 15,
            "Bi": 0,
            "U": 3,
            "REE": 21
        },
        "Fe": {
            "Fe": 1364,
            "Ni": 57,
            "Cu": 128,
            "Zn": 88,
            "As": 153,
            "Se": 9,
            "Ag": 22,
            "Sb": 45,
            "Ba": 68,
            "Pb": 87,
            "Bi": 19,
            "U": 28,
            "REE": 86
        },
        "Ni": {
            "Ni": 57,
            "Cu": 10,
            "Zn": 0,
            "As": 6,
            "Se": 0,
            "Ag": 1,
            "Sb": 2,
            "Ba": 2,
            "Pb": 3,
            "Bi": 0,
            "U": 0,
            "REE": 0
        },
        "Cu": {
            "Cu": 128,
            "Zn": 14,
            "As": 32,
            "Se": 5,
            "Ag": 7,
            "Sb": 8,
            "Ba": 2,
            "Pb": 14,
            "Bi": 9,
            "U": 0,
            "REE": 1
        },
        "Zn": {
            "Zn": 88,
            "As": 16,
            "Se": 0,
            "Ag": 3,
            "Sb": 2,
            "Ba": 0,
            "Pb": 8,
            "Bi": 0,
            "U": 2,
            "REE": 3
        },
        "As": {
            "As": 153,
            "Se": 1,
            "Ag": 5,
            "Sb": 9,
            "Ba": 3,
            "Pb": 16,
            "Bi": 5,
            "U": 2,
            "REE": 5
        },
        "Se": {
            "Se": 9,
            "Ag": 1,
            "Sb": 1,
            "Ba": 0,
            "Pb": 0,
            "Bi": 0,
            "U": 0,
            "REE": 0
        },
        "Ag": {
            "Ag": 22,
            "Sb": 8,
            "Ba": 0,
            "Pb": 4,
            "Bi": 2,
            "U": 0,
            "REE": 0
        },
        "Sb": {
            "Sb": 45,
            "Ba": 0,
            "Pb": 9,
            "Bi": 3,
            "U": 0,
            "REE": 0
        },
        "Ba": {
            "Ba": 68,
            "Pb": 3,
            "Bi": 0,
            "U": 1,
            "REE": 4
        },
        "Pb": {
            "Pb": 87,
            "Bi": 6,
            "U": 7,
            "REE": 6
        },
        "Bi": {
            "Bi": 19,
            "U": 0,
            "REE": 0
        },
        "U": {
            "U": 28,
            "REE": 9
        },
        "REE": {
            "REE": 86
        }
    }
}